peid/VERSION.txt
peid/__info__.py
peid/__init__.py
peid/__main__.py
peid/db/.userdb_txt.json
peid/db/__init__.py
peid/db/userdb.txt
peid/exe/__init__.py
peid/exe/msdos.py
peid/exe/pe.py
peid-2.2.1.dist-info/LICENSE
peid-2.2.1.dist-info/METADATA
peid-2.2.1.dist-info/WHEEL
peid-2.2.1.dist-info/entry_points.txt
peid-2.2.1.dist-info/top_level.txt
peid-2.2.1.dist-info/RECORD
