Metadata-Version: 2.1
Name: peid
Version: 2.2.1
Summary: Python implementation of the Packed Executable iDentifier (PEiD)
Author-email: Alexandre D'Hondt <alexandre.dhondt@gmail.com>
License: GNU GENERAL PUBLIC LICENSE
Project-URL: homepage, https://github.com/packing-box/peid
Project-URL: issues, https://github.com/packing-box/peid/issues
Project-URL: repository, https://github.com/packing-box/peid
Keywords: packing,packed-executable,packing-detection,pe
Classifier: Development Status :: 5 - Production/Stable
Classifier: Environment :: Console
Classifier: Intended Audience :: Developers
Classifier: Intended Audience :: Information Technology
Classifier: Intended Audience :: Other Audience
Classifier: License :: OSI Approved :: GNU General Public License v3 or later (GPLv3+)
Classifier: Programming Language :: Python :: 3
Classifier: Programming Language :: Python :: 3 :: Only
Classifier: Programming Language :: Python :: 3.8
Classifier: Programming Language :: Python :: 3.9
Classifier: Programming Language :: Python :: 3.10
Classifier: Programming Language :: Python :: 3.11
Classifier: Topic :: Software Development :: Libraries :: Python Modules
Classifier: Topic :: Security
Requires-Python: <4,>=3.8
License-File: LICENSE
Requires-Dist: msgspec
